mittens/__init__.py
mittens/doc.py
mittens/mittens_base.py
mittens/np_mittens.py
mittens/tf_mittens.py
mittens-0.2.dist-info/LICENSE
mittens-0.2.dist-info/METADATA
mittens-0.2.dist-info/WHEEL
mittens-0.2.dist-info/top_level.txt
mittens-0.2.dist-info/RECORD
